{
  "keywords": [
    {
      "keyword": "메타",
      "score": 1.0377700310997342
    },
    {
      "keyword": "삼성",
      "score": 0.6497684436304889
    },
    {
      "keyword": "애플",
      "score": 0.6216222180646412
    },
    {
      "keyword": "중국",
      "score": 0.5204222277571107
    },
    {
      "keyword": "디스플레이",
      "score": 0.5102660655507482
    },
    {
      "keyword": "패널",
      "score": 0.456666353046759
    },
    {
      "keyword": "게임",
      "score": 0.40181903133435776
    },
    {
      "keyword": "구글",
      "score": 0.36864076809879814
    },
    {
      "keyword": "장비",
      "score": 0.34597522562338706
    },
    {
      "keyword": "안경",
      "score": 0.3310436368620837
    },
    {
      "keyword": "기기",
      "score": 0.3301760856980623
    },
    {
      "keyword": "건설",
      "score": 0.3197677344698404
    },
    {
      "keyword": "아이폰",
      "score": 0.30780237153002554
    },
    {
      "keyword": "경쟁",
      "score": 0.30410332215948516
    },
    {
      "keyword": "OLED",
      "score": 0.29199309063831846
    },
    {
      "keyword": "6세대",
      "score": 0.2918325395811592
    },
    {
      "keyword": "유플러스",
      "score": 0.2888576185183898
    },
    {
      "keyword": "마이크",
      "score": 0.28818739198669124
    },
    {
      "keyword": "브레이커스",
      "score": 0.28471719989320754
    },
    {
      "keyword": "규모",
      "score": 0.28392983774740926
    }
  ]
}