{
  "timestamp": "2025-10-07T08:45:00Z",
  "matrix_stats": {
    "num_orgs": 41,
    "num_topics": 14,
    "top_org": "AMD"
  },
  "network_stats": {
    "num_nodes": 30,
    "num_edges": 35,
    "top_pairs": [
      {
        "source": "삼성전자",
        "target": "애플",
        "weight": 12,
        "rel_type": "rivalry"
      },
      {
        "source": "삼성디스플레이",
        "target": "삼성전자",
        "weight": 12,
        "rel_type": "rivalry"
      },
      {
        "source": "삼성디스플레이",
        "target": "애플",
        "weight": 9,
        "rel_type": "rivalry"
      },
      {
        "source": "삼성전자",
        "target": "현대모비스",
        "weight": 6,
        "rel_type": "rivalry"
      },
      {
        "source": "LG전자",
        "target": "삼성전자",
        "weight": 6,
        "rel_type": "rivalry"
      }
    ],
    "top_hub": "삼성전자"
  }
}