{
  "keywords": [
    {
      "keyword": "삼성",
      "score": 0.6429343046575253
    },
    {
      "keyword": "디스플레이",
      "score": 0.5536290091167049
    },
    {
      "keyword": "메타",
      "score": 0.5445898942413273
    },
    {
      "keyword": "애플",
      "score": 0.5412435547453788
    },
    {
      "keyword": "반도체",
      "score": 0.4879402698662436
    },
    {
      "keyword": "미국",
      "score": 0.4077044774577364
    },
    {
      "keyword": "패널",
      "score": 0.38425438247159766
    },
    {
      "keyword": "중국",
      "score": 0.3680740334715995
    },
    {
      "keyword": "아이",
      "score": 0.3532411616640997
    },
    {
      "keyword": "퀄컴",
      "score": 0.332132852679897
    },
    {
      "keyword": "경쟁",
      "score": 0.31859719103891065
    },
    {
      "keyword": "1위",
      "score": 0.30474669744367733
    },
    {
      "keyword": "브레이커스",
      "score": 0.28474522621548026
    },
    {
      "keyword": "장비",
      "score": 0.2685889657137817
    },
    {
      "keyword": "청소",
      "score": 0.2650666582163163
    },
    {
      "keyword": "생산",
      "score": 0.26105336423115627
    },
    {
      "keyword": "마이크",
      "score": 0.25525488126586904
    },
    {
      "keyword": "6세대",
      "score": 0.25419009575007184
    },
    {
      "keyword": "화재",
      "score": 0.24505692107823776
    },
    {
      "keyword": "관세",
      "score": 0.2428599653676371
    }
  ]
}