{
  "ideas": [
    {
      "idea": "AI 기반 디스플레이 공정 자동화 및 수율 개선 솔루션",
      "problem": "디스플레이 제조 공정은 복잡하고 정밀하여 수율 관리가 중요하지만, 숙련된 엔지니어의 경험에 의존하는 경우가 많아 효율성이 떨어집니다. AI 기술을 활용하여 공정 데이터를 분석하고 자동화함으로써 수율을 획기적으로 개선할 필요가 있습니다.",
      "target_customer": "국내외 디스플레이 패널 제조사 (LG디스플레이, 삼성디스플레이, BOE)",
      "value_prop": "AI 기반 실시간 공정 데이터 분석 및 예측 모델을 통해 불량 발생 가능성을 사전에 감지하고 예방. 공정 자동화 및 최적화로 생산 효율성 향상 및 비용 절감. 경쟁사 대비 높은 수율 및 생산성 확보.",
      "solution": [
        "AI 기반 공정 데이터 분석 및 예측 모델 개발",
        "자동화된 공정 제어 시스템 구축",
        "머신 러닝 기반 불량 원인 분석 및 개선",
        "실시간 공정 모니터링 및 이상 감지 시스템"
      ],
      "risks": [
        "AI 모델의 정확성 및 신뢰성 확보",
        "데이터 보안 및 개인 정보 보호",
        "기존 설비와의 호환성 문제"
      ],
      "priority_score": 4.5,
      "title": "AI 기반 디스플레이 공정 자동화 및 수율 개선 솔루션",
      "score": 31.0,
      "evidence": [
        {
          "sentence": "혁신의 중심은 포르쉐 역사상 가장 큰 디스플레이인 플로우 디스플레이 (Flow Dis-play)로 우아한 곡면 디자인으로 매끄럽게 통합되어 직관적인 조작이 가능하다.",
          "url": "https://www.sportsworldi.com/newsView/20251002508856",
          "date": "2025-10-02"
        },
        {
          "sentence": "스타일 포르쉐 인테리어 총괄 마커스 아우어바흐 (Markus Auerbach)는 “카이엔 고유의 특성과 새로 개발된 디스플레이, 그리고 포르쉐 디지털 인터랙션 기능을 전체 패키지로 조화롭게 통합하는 것이 가장 중요한 목표였다”며, “혁신과 미래지향성을 바탕으로 디테일까지 세심하게 설계되어 인테리어 경험의 새로운 기준을 제시한다”고 강조했다.",
          "url": "https://www.sportsworldi.com/newsView/20251002508856",
          "date": "2025-10-02"
        },
        {
          "sentence": "특히, 새로운 포르쉐 디지털 인터랙션 (Porsche Digital Interaction) 디스플레이 및 작동 콘셉트는 곡선형 OLED 패널의 ‘플로우 디스플레이 (Flow Display)’를 통해 디지털화의 새로운 이정표를 제시한다.",
          "url": "https://www.sportsworldi.com/newsView/20251002508856",
          "date": "2025-10-02"
        }
      ],
      "score_breakdown": {
        "market": 0.225,
        "urgency": 0.2,
        "feasibility": 0.6,
        "risk": 0.0,
        "notes": {
          "cur": 0,
          "z_like": 0.0
        }
      }
    },
    {
      "idea": "AI 기반 차량용 HUD 개인 맞춤형 솔루션",
      "problem": "차량용 HUD는 운전자에게 중요한 정보를 제공하지만, 운전자의 시력, 자세, 선호도에 따른 개인화 기능이 부족하여 정보 인지도가 떨어지고 피로감을 유발할 수 있습니다. AI 기술 발전으로 실시간 운전자 맞춤형 정보 제공의 필요성이 커지고 있습니다.",
      "target_customer": "글로벌 완성차 OEM (Tier 1 부품사 협력)",
      "value_prop": "AI 기반 시선 추적 및 증강 현실 기술을 통해 운전자에게 최적화된 HUD 정보 제공. 안전 운전 지원 및 사용자 경험 극대화. 경쟁사 대비 높은 정보 인지율 및 낮은 피로도 제공.",
      "solution": [
        "AI 기반 시선 추적 및 운전자 자세 분석",
        "AR 기반 내비게이션 및 위험 경고 정보 표시",
        "개인별 시력 및 선호도에 따른 HUD 화면 최적화",
        "클라우드 기반 데이터 분석 및 지속적인 성능 개선"
      ],
      "risks": [
        "AI 알고리즘의 안전성 및 신뢰성 확보",
        "개인 정보 보호 규제 준수",
        "높은 초기 개발 비용 및 기술적 난이도"
      ],
      "priority_score": 4.2,
      "title": "AI 기반 차량용 HUD 개인 맞춤형 솔루션",
      "score": 30.4,
      "evidence": [
        {
          "sentence": "카이엔은 증강현실 (AR) 기반의 헤드업 디스플레이를 지원하며 유효 디스플레이 면적은 최대 87인치에 달한다.",
          "url": "https://www.sportsworldi.com/newsView/20251002508856",
          "date": "2025-10-02"
        },
        {
          "sentence": "이 밖에도, AI기반 보이스 파일럿으로 한층 진화된 사용자 경험을 제공한다.",
          "url": "https://www.sportsworldi.com/newsView/20251002508856",
          "date": "2025-10-02"
        },
        {
          "sentence": "무단전재-재배포 및 AI학습 이용 금지.",
          "url": "https://www.nspna.com/news/?mode=view&newsid=780610",
          "date": "2025-10-02"
        }
      ],
      "score_breakdown": {
        "market": 0.21,
        "urgency": 0.2,
        "feasibility": 0.6,
        "risk": 0.0,
        "notes": {
          "cur": 0,
          "z_like": 0.0
        }
      }
    },
    {
      "idea": "마이크로 LED 기반 AR 글래스용 초고휘도 모듈",
      "problem": "AR 글래스는 몰입감 있는 사용자 경험을 위해 높은 밝기와 해상도를 요구하지만, 기존 디스플레이 기술로는 충분한 성능을 제공하기 어렵습니다. 특히 야외 환경에서의 시인성 확보가 중요한 과제이며, 마이크로 LED 기술이 대안으로 부상하고 있습니다.",
      "target_customer": "북미 빅테크 기업 (AR/VR 디바이스 제조사)",
      "value_prop": "기존 AR 글래스 대비 5배 이상 높은 휘도와 넓은 색 영역을 제공하여 몰입감 극대화. 초소형, 저전력 설계로 AR 글래스 디자인 자유도 향상. 경쟁사 대비 뛰어난 야외 시인성 확보.",
      "solution": [
        "마이크로 LED 전사 및 패키징 기술",
        "고효율 광학 설계 및 렌즈 기술",
        "초고휘도 및 넓은 색 영역 구현",
        "소형화 및 저전력 설계"
      ],
      "risks": [
        "마이크로 LED 전사 및 수율 문제",
        "높은 생산 비용 및 가격 경쟁력 확보",
        "AR 글래스 시장의 성장 속도 불확실성"
      ],
      "priority_score": 3.9,
      "title": "마이크로 LED 기반 AR 글래스용 초고휘도 모듈",
      "score": 29.8,
      "evidence": [
        {
          "sentence": "특히, 새로운 포르쉐 디지털 인터랙션 (Porsche Digital Interaction) 디스플레이 및 작동 콘셉트는 곡선형 OLED 패널의 ‘플로우 디스플레이 (Flow Display)’를 통해 디지털화의 새로운 이정표를 제시한다.",
          "url": "https://www.sportsworldi.com/newsView/20251002508856",
          "date": "2025-10-02"
        },
        {
          "sentence": "14.25인치 OLED의 풀 디지털 계기판은 파워 미터, 내비게이션, 주행 보조 시스템, 인포테인먼트 등 주요 정보를 명확하게 표시한다.",
          "url": "https://www.sportsworldi.com/newsView/20251002508856",
          "date": "2025-10-02"
        },
        {
          "sentence": "카이엔은 증강현실 (AR) 기반의 헤드업 디스플레이를 지원하며 유효 디스플레이 면적은 최대 87인치에 달한다.",
          "url": "https://www.sportsworldi.com/newsView/20251002508856",
          "date": "2025-10-02"
        }
      ],
      "score_breakdown": {
        "market": 0.195,
        "urgency": 0.2,
        "feasibility": 0.6,
        "risk": 0.0,
        "notes": {
          "cur": 0,
          "z_like": 0.0
        }
      }
    },
    {
      "idea": "IT 기기용 벤더블 OLED 패널 솔루션",
      "problem": "노트북, 태블릿 등 IT 기기 시장에서 폴더블, 롤러블 디스플레이에 대한 수요가 증가하고 있지만, 기존 OLED 패널은 내구성 및 벤딩 성능에 한계가 있습니다. 특히, 중국의 OLED 패널 생산량 증가로 경쟁이 심화됨에 따라 차별화된 기술 확보가 중요합니다.",
      "target_customer": "글로벌 IT 기기 제조사 (삼성, LG, Apple)",
      "value_prop": "기존 OLED 대비 2배 이상 높은 벤딩 내구성과 얇은 두께를 제공하여 혁신적인 디자인 구현. 뛰어난 화질과 넓은 시야각으로 사용자 경험 향상. 경쟁사 대비 높은 신뢰성 및 긴 수명 보장.",
      "solution": [
        "신규 Flexible 기판 소재 개발",
        "최적화된 박막 봉지 기술 적용",
        "스트레스 분산 설계 및 공정 기술",
        "고해상도 및 저전력 구동 기술"
      ],
      "risks": [
        "신규 소재의 안정성 및 신뢰성 확보",
        "양산 수율 확보 및 생산 비용 절감",
        "폴더블/롤러블 IT 기기 시장의 성장 불확실성"
      ],
      "priority_score": 3.7,
      "title": "IT 기기용 벤더블 OLED 패널 솔루션",
      "score": 29.4,
      "evidence": [
        {
          "sentence": "새로운 표면 발열 시스템을 통해 시트는 물론 팔걸이와 도어 패널 등 넓은 접촉면을 따뜻하게 해준다.",
          "url": "https://www.sportsworldi.com/newsView/20251002508856",
          "date": "2025-10-02"
        },
        {
          "sentence": "특히, 새로운 포르쉐 디지털 인터랙션 (Porsche Digital Interaction) 디스플레이 및 작동 콘셉트는 곡선형 OLED 패널의 ‘플로우 디스플레이 (Flow Display)’를 통해 디지털화의 새로운 이정표를 제시한다.",
          "url": "https://www.sportsworldi.com/newsView/20251002508856",
          "date": "2025-10-02"
        },
        {
          "sentence": "G03-8236672469 fullscreen (서울=NSP통신) 이복현 기자 = 한국 OLED 패널 업체들이 3분기 들어 출하량에서 뚜렷한 반등세를 나타냈다.",
          "url": "https://www.nspna.com/news/?mode=view&newsid=780610",
          "date": "2025-10-02"
        }
      ],
      "score_breakdown": {
        "market": 0.185,
        "urgency": 0.2,
        "feasibility": 0.6,
        "risk": 0.0,
        "notes": {
          "cur": 0,
          "z_like": 0.0
        }
      }
    },
    {
      "idea": "퀀텀닷 컬러 필터 기반 LCD 고색재현율 솔루션",
      "problem": "LCD는 OLED 대비 색재현율이 낮아 프리미엄 디스플레이 시장에서 경쟁력이 약화되고 있습니다. 퀀텀닷 기술은 LCD의 색재현율을 향상시킬 수 있지만, 기존 퀀텀닷 컬러 필터는 생산 비용이 높고 균일한 품질을 유지하기 어렵습니다.",
      "target_customer": "글로벌 TV 제조사 (삼성, LG, TCL)",
      "value_prop": "기존 퀀텀닷 컬러 필터 대비 낮은 생산 비용으로 OLED 수준의 색재현율 구현. 균일한 품질과 높은 신뢰성 제공. 기존 LCD 생산 라인에 적용 가능하여 투자 비용 절감.",
      "solution": [
        "고효율 퀀텀닷 소재 개발",
        "정밀 코팅 및 패턴 형성 기술",
        "균일한 두께 및 색상 제어 기술",
        "기존 LCD 생산 라인 호환성 확보"
      ],
      "risks": [
        "퀀텀닷 소재의 환경 규제 준수",
        "색상 균일성 및 신뢰성 확보",
        "OLED 기술 발전 속도에 따른 경쟁력 약화 가능성"
      ],
      "priority_score": 3.3,
      "title": "퀀텀닷 컬러 필터 기반 LCD 고색재현율 솔루션",
      "score": 28.6,
      "evidence": [
        {
          "sentence": "솔벤텀은 2024년 4월 3M 헬스케어 사업부에서 분사한 뒤 기존 정수·필터 기술을 기반으로 아쿠아퓨어 브랜드를 새롭게 리브랜딩했다.",
          "url": "https://it.chosun.com/news/articleView.html?idxno=2023092148455",
          "date": "2025-10-02"
        },
        {
          "sentence": "특히 필터 관리 편의성을 강화됐다.",
          "url": "https://it.chosun.com/news/articleView.html?idxno=2023092148455",
          "date": "2025-10-02"
        },
        {
          "sentence": "하나의 고성능 필터로 다단계 정수 기능을 수행할 수 있다.",
          "url": "https://it.chosun.com/news/articleView.html?idxno=2023092148455",
          "date": "2025-10-02"
        }
      ],
      "score_breakdown": {
        "market": 0.165,
        "urgency": 0.2,
        "feasibility": 0.6,
        "risk": 0.0,
        "notes": {
          "cur": 0,
          "z_like": 0.0
        }
      }
    }
  ]
}